ms_collect/__init__.py
ms_collect/collection.py
ms_collect/envelope.py
ms_collect/math.py
ms_collect/point.py
ms_collect/scope.py
ms_collect/trace.py
ms_collect/utils.py
ms_collect/viz/__init__.py
ms_collect/viz/bar.py
ms_collect/viz/scatter.py
ms_collect-0.0.4.dist-info/LICENSE
ms_collect-0.0.4.dist-info/METADATA
ms_collect-0.0.4.dist-info/WHEEL
ms_collect-0.0.4.dist-info/top_level.txt
ms_collect-0.0.4.dist-info/RECORD
