Metadata-Version: 2.1
Name: ms-collect
Version: 0.0.4
Summary: A series of modules that provide easy storage/accesss to Mass Spec related Raw Data/Groupings of Data.
Home-page: https://github.com/jakuzo/ms-collect
Author: jakuzo
Author-email: jackcampanella@protonmail.com
License: UNKNOWN
Project-URL: Bug Tracker, https://github.com/jakuzo/ms-collect/issues
Platform: UNKNOWN
Classifier: Programming Language :: Python :: 3
Classifier: License :: OSI Approved :: MIT License
Classifier: Operating System :: OS Independent
Requires-Python: >=3.7
License-File: LICENSE
Requires-Dist: matplotlib
